setup.py
rapier.egg-info/PKG-INFO
rapier.egg-info/SOURCES.txt
rapier.egg-info/dependency_links.txt
rapier.egg-info/entry_points.txt
rapier.egg-info/requires.txt
rapier.egg-info/top_level.txt
util/__init__.py
util/gen_html.py
util/gen_js_sdk.py
util/gen_openapispec.py
util/gen_py_sdk.py
util/rapier.py
util/validate_rapier.py