Metadata-Version: 1.0
Name: rapier
Version: 0.0.3
Summary: Generate OpenAPI specification from Rapier specification
Home-page: https://github.com/apigee-labs/rapier
Author: Martin Nally
Author-email: mnally@apigee.com
License: UNKNOWN
Platform: UNKNOWN
